dseval/__init__.py
dseval/agent.py
dseval/limit.py
dseval/limit_test.py
dseval/logging.py
dseval/loop.py
dseval/match.py
dseval/match_test.py
dseval/problem.py
dseval/simulation.py
dseval/simulation_test.py
dseval/utils.py
dseval/validator.py
dseval/validator_test.py
dseval-0.0.1.dist-info/METADATA
dseval-0.0.1.dist-info/WHEEL
dseval-0.0.1.dist-info/licenses/LICENSE
dseval-0.0.1.dist-info/RECORD
